tno/quantum/ml/classifiers/__init__.py
tno/quantum/ml/classifiers/py.typed
tno/quantum/ml/classifiers/test/__init__.py
tno/quantum/ml/classifiers/test/test_classification.py
tno_quantum_ml_classifiers-1.0.0.dist-info/licenses/LICENSE
tno_quantum_ml_classifiers-1.0.0.dist-info/METADATA
tno_quantum_ml_classifiers-1.0.0.dist-info/WHEEL
tno_quantum_ml_classifiers-1.0.0.dist-info/top_level.txt
tno_quantum_ml_classifiers-1.0.0.dist-info/RECORD
